Metadata-Version: 2.1
Name: example-package-vegadelalyra
Version: 0.0.1
Summary: A small example package
Author-email: vegadelalyra <lyradeperseo@gmail.com>
Project-URL: Homepage, https://github.com/vegadelalyra/poll-django
Project-URL: Bug Tracker, https://github.com/pypa/sampleproject/issues
Classifier: Programming Language :: Python :: 3
Classifier: License :: OSI Approved :: MIT License
Classifier: Operating System :: OS Independent
Requires-Python: >=3.7
License-File: LICENSE
